Metadata-Version: 2.1
Name: explore-lif
Version: 0.1.1
Summary: A Python module for loading lif file as numpy array
Home-page: https://github.com/yangyushi/explore_lif
Author: Yushi Yang
Author-email: yangyushi1992@icloud.com
License: UNKNOWN
Platform: UNKNOWN
Requires-Python: >=2.5
